{
  "merch_sold_out": false,
  "label_id": 2241322701,
  "currency": "EUR",
  "featured_track_id": 2809477874,
  "package_art": [
    8919678,
    8920416,
    8920418,
    8920423,
    8920422,
    9250446,
    9250442,
    9250443,
    9250445,
    12946807,
    12946810,
    12946811,
    12946812,
    12946813
  ],
  "bandcamp_url": "https://schnaussandmunk.bandcamp.com/album/passage-2",
  "type": "a",
  "package_details_lite": {
    "513414282": {
      "title": "CD",
      "image_ids": [
        8919678,
        8920416,
        8920418,
        8920423,
        8920422
      ]
    },
    "885645241": {
      "title": "2018 edition, transparent yellow vinyl",
      "image_ids": [
        12946807,
        12946810,
        12946811,
        12946812,
        12946813
      ]
    },
    "3030243874": {
      "title": "First pressing, black vinyl",
      "image_ids": [
        9250446,
        9250442,
        9250443,
        9250445
      ]
    }
  },
  "album_title": "PASSAGE",
  "album_id": 1670971920,
  "label": "Azure Vista Records",
  "free_download": false,
  "is_purchasable": true,
  "is_set_price": true,
  "tralbum_artist": "Ulrich Schnauss & Jonas Munk",
  "tracks": [
    {
      "label_id": 2241322701,
      "currency": "EUR",
      "merch_sold_out": null,
      "has_lyrics": false,
      "album_id": 1670971920,
      "album_title": null,
      "label": "Azure Vista Records",
      "is_purchasable": false,
      "duration": 320.597,
      "track_license_id": null,
      "is_set_price": false,
      "is_streamable": true,
      "track_num": 1,
      "title": "Amaris",
      "track_id": 2809477874,
      "has_digital_download": false,
      "streaming_url": {
        "mp3-128": "https://bandcamp.com/stream_redirect?enc=mp3-128&track_id=2809477874&ts=1648908531&t=4dadbad1af4927130b1dac2cad5f8da2868e2f42"
      },
      "require_email": false,
      "merch_ids": null,
      "art_id": null,
      "band_name": "Ulrich Schnauss & Jonas Munk",
      "encodings_id": 2217143372,
      "band_id": 3454424886,
      "price": null
    },
    {
      "label_id": 2241322701,
      "currency": "EUR",
      "merch_sold_out": null,
      "has_lyrics": false,
      "album_id": 1670971920,
      "album_title": null,
      "label": "Azure Vista Records",
      "is_purchasable": false,
      "duration": 336,
      "track_license_id": null,
      "is_set_price": false,
      "is_streamable": false,
      "track_num": 2,
      "title": "Genau Wie Damals",
      "track_id": 3912039757,
      "has_digital_download": false,
      "streaming_url": null,
      "require_email": false,
      "merch_ids": null,
      "art_id": null,
      "band_name": "Ulrich Schnauss & Jonas Munk",
      "encodings_id": 168238271,
      "band_id": 3454424886,
      "price": null
    },
    {
      "label_id": 2241322701,
      "currency": "EUR",
      "merch_sold_out": null,
      "has_lyrics": false,
      "album_id": 1670971920,
      "album_title": null,
      "label": "Azure Vista Records",
      "is_purchasable": false,
      "duration": 275.368,
      "track_license_id": null,
      "is_set_price": false,
      "is_streamable": true,
      "track_num": 3,
      "title": "Anywhere But Here",
      "track_id": 424931237,
      "has_digital_download": false,
      "streaming_url": {
        "mp3-128": "https://bandcamp.com/stream_redirect?enc=mp3-128&track_id=424931237&ts=1648908531&t=f91a6cca4bea44b57833163ac326ccae465748b0"
      },
      "require_email": false,
      "merch_ids": null,
      "art_id": null,
      "band_name": "Ulrich Schnauss & Jonas Munk",
      "encodings_id": 2175478893,
      "band_id": 3454424886,
      "price": null
    },
    {
      "label_id": 2241322701,
      "currency": "EUR",
      "merch_sold_out": null,
      "has_lyrics": false,
      "album_id": 1670971920,
      "album_title": null,
      "label": "Azure Vista Records",
      "is_purchasable": false,
      "duration": 110,
      "track_license_id": null,
      "is_set_price": false,
      "is_streamable": false,
      "track_num": 4,
      "title": "Intervention: Sol",
      "track_id": 944400612,
      "has_digital_download": false,
      "streaming_url": null,
      "require_email": false,
      "merch_ids": null,
      "art_id": null,
      "band_name": "Ulrich Schnauss & Jonas Munk",
      "encodings_id": 2366432435,
      "band_id": 3454424886,
      "price": null
    },
    {
      "label_id": 2241322701,
      "currency": "EUR",
      "merch_sold_out": null,
      "has_lyrics": false,
      "album_id": 1670971920,
      "album_title": null,
      "label": "Azure Vista Records",
      "is_purchasable": false,
      "duration": 301.091,
      "track_license_id": null,
      "is_set_price": false,
      "is_streamable": false,
      "track_num": 5,
      "title": "MST",
      "track_id": 2413476191,
      "has_digital_download": false,
      "streaming_url": null,
      "require_email": false,
      "merch_ids": null,
      "art_id": null,
      "band_name": "Ulrich Schnauss & Jonas Munk",
      "encodings_id": 1247941192,
      "band_id": 3454424886,
      "price": null
    },
    {
      "label_id": 2241322701,
      "currency": "EUR",
      "merch_sold_out": null,
      "has_lyrics": false,
      "album_id": 1670971920,
      "album_title": null,
      "label": "Azure Vista Records",
      "is_purchasable": false,
      "duration": 362.182,
      "track_license_id": null,
      "is_set_price": false,
      "is_streamable": false,
      "track_num": 6,
      "title": "Ao Hinode",
      "track_id": 3596488597,
      "has_digital_download": false,
      "streaming_url": null,
      "require_email": false,
      "merch_ids": null,
      "art_id": null,
      "band_name": "Ulrich Schnauss & Jonas Munk",
      "encodings_id": 1997304830,
      "band_id": 3454424886,
      "price": null
    },
    {
      "label_id": 2241322701,
      "currency": "EUR",
      "merch_sold_out": null,
      "has_lyrics": false,
      "album_id": 1670971920,
      "album_title": null,
      "label": "Azure Vista Records",
      "is_purchasable": false,
      "duration": 255.882,
      "track_license_id": null,
      "is_set_price": false,
      "is_streamable": true,
      "track_num": 7,
      "title": "Spellbreaker",
      "track_id": 3607418583,
      "has_digital_download": false,
      "streaming_url": {
        "mp3-128": "https://bandcamp.com/stream_redirect?enc=mp3-128&track_id=3607418583&ts=1648908531&t=0dc1754c3032f901b1400c308f6477f7617368ec"
      },
      "require_email": false,
      "merch_ids": null,
      "art_id": null,
      "band_name": "Ulrich Schnauss & Jonas Munk",
      "encodings_id": 768310213,
      "band_id": 3454424886,
      "price": null
    },
    {
      "label_id": 2241322701,
      "currency": "EUR",
      "merch_sold_out": null,
      "has_lyrics": false,
      "album_id": 1670971920,
      "album_title": null,
      "label": "Azure Vista Records",
      "is_purchasable": false,
      "duration": 166.737,
      "track_license_id": null,
      "is_set_price": false,
      "is_streamable": false,
      "track_num": 8,
      "title": "Intervention: Stjerner",
      "track_id": 338855836,
      "has_digital_download": false,
      "streaming_url": null,
      "require_email": false,
      "merch_ids": null,
      "art_id": null,
      "band_name": "Ulrich Schnauss & Jonas Munk",
      "encodings_id": 2803387795,
      "band_id": 3454424886,
      "price": null
    },
    {
      "label_id": 2241322701,
      "currency": "EUR",
      "merch_sold_out": null,
      "has_lyrics": false,
      "album_id": 1670971920,
      "album_title": null,
      "label": "Azure Vista Records",
      "is_purchasable": false,
      "duration": 324,
      "track_license_id": null,
      "is_set_price": false,
      "is_streamable": false,
      "track_num": 9,
      "title": "Caffeine Blues",
      "track_id": 3677414470,
      "has_digital_download": false,
      "streaming_url": null,
      "require_email": false,
      "merch_ids": null,
      "art_id": null,
      "band_name": "Ulrich Schnauss & Jonas Munk",
      "encodings_id": 2331485355,
      "band_id": 3454424886,
      "price": null
    },
    {
      "label_id": 2241322701,
      "currency": "EUR",
      "merch_sold_out": null,
      "has_lyrics": false,
      "album_id": 1670971920,
      "album_title": null,
      "label": "Azure Vista Records",
      "is_purchasable": false,
      "duration": 111,
      "track_license_id": null,
      "is_set_price": false,
      "is_streamable": true,
      "track_num": 10,
      "title": "Intervention: Måne",
      "track_id": 2148164096,
      "has_digital_download": false,
      "streaming_url": {
        "mp3-128": "https://bandcamp.com/stream_redirect?enc=mp3-128&track_id=2148164096&ts=1648908531&t=26a22e732da9f43ca41184b23573dffe1f3a95fe"
      },
      "require_email": false,
      "merch_ids": null,
      "art_id": null,
      "band_name": "Ulrich Schnauss & Jonas Munk",
      "encodings_id": 779656729,
      "band_id": 3454424886,
      "price": null
    },
    {
      "label_id": 2241322701,
      "currency": "EUR",
      "merch_sold_out": null,
      "has_lyrics": false,
      "album_id": 1670971920,
      "album_title": null,
      "label": "Azure Vista Records",
      "is_purchasable": false,
      "duration": 455.455,
      "track_license_id": null,
      "is_set_price": false,
      "is_streamable": false,
      "track_num": 11,
      "title": "Coastal Path",
      "track_id": 2720266218,
      "has_digital_download": false,
      "streaming_url": null,
      "require_email": false,
      "merch_ids": null,
      "art_id": null,
      "band_name": "Ulrich Schnauss & Jonas Munk",
      "encodings_id": 1222129929,
      "band_id": 3454424886,
      "price": null
    }
  ],
  "title": "PASSAGE",
  "num_downloadable_tracks": 11,
  "has_digital_download": true,
  "tags": [
    {
      "geoname": null,
      "loc_id": null,
      "norm_name": "azure-vista-records",
      "isloc": false,
      "url": "/tag/azure-vista-records",
      "name": "Azure Vista Records"
    },
    {
      "geoname": null,
      "loc_id": null,
      "norm_name": "jazz",
      "isloc": false,
      "url": "/tag/jazz",
      "name": "Jazz"
    },
    {
      "geoname": {
        "fullname": "Oakland, California",
        "name": "Oakland",
        "id": 5378538
      },
      "loc_id": 2850659308,
      "norm_name": "oakland",
      "isloc": true,
      "url": "/tag/oakland",
      "name": "Oakland"
    }
  ],
  "about": "”Passage” is the second collaborative album from London-based synth-wizard Ulrich Schnauss and Danish producer Jonas Munk. 11 tracks of breezy, blissed-out electronica and multi-coloured ambient. \r\n\r\nAs the album title denotes, there's a sense of movement in the music these two producers create together: a Schnauss & Munk composition starts one place and ends up someplace very different – something that can only rarely be said about electronic music, which traditionally has focused it's energy on texture rather than composition. Sometimes their vivid, expansive soundscapes feels like the sonic equivalent of gliding towards the horizon through a panoramic landscape on a train. One's perspective changes slightly when in motion from one place to another – continously approaching new things and leaving others behind. Listening to the album in it's entirety feels like an emotional passage, or one that plays out via a series of dreams.\r\n\r\nThere's a prismatic, multi-dimensional quality to these 11 tracks, likely stemming from the fact that these two producers each have worked with a wide range of styles and musicians throughout their 15+ year career. Both Ulrich and Jonas, however, have the skills of seasoned producers to weave the multitude of influences together in a well-defined sonic aesthetic. The result is a compelling set of melodic electronic music that echoes the past, yet feels fresh.",
  "is_preorder": false,
  "streaming_limit": 3,
  "require_email": false,
  "credits": null,
  "art_id": 3809045440,
  "id": 1670971920,
  "price": 6,
  "release_date": 1484870400,
  "band": {
    "bio": null,
    "location": "London, UK",
    "image_id": 8579411,
    "name": "Ulrich Schnauss & Jonas Munk",
    "band_id": 3454424886
  }
}
