{
  "modulePrefix": "web-tv-app",
  "environment": "production",
  "rootURL": "/",
  "locationType": "auto",
  "historySupportMiddleware": true,
  "exportApplicationGlobal": false,
  "i18n": {
    "defaultLocale": "en-GB",
    "useDevLoc": false
  },
  "ember-cli-mirage": {
    "enabled": false,
    "usingProxy": false,
    "useDefaultPassthroughs": true
  },
  "SASSKIT_GENERATOR": {
    "VIEWPORT_CONFIG": {
      "BREAKPOINTS": {
        "xsmall": {
          "min": 300,
          "max": 739
        },
        "small": {
          "min": 740,
          "max": 999
        },
        "medium": {
          "min": 1000,
          "max": 1319
        },
        "large": {
          "min": 1320,
          "max": 1679
        },
        "xlarge": {
          "min": 1680,
          "content": 1680
        }
      }
    }
  },
  "METRICS": {
    "baseFields": {
      "appName": "com.apple.tv",
      "delegateApp": "web-tv-app",
      "constraintProfiles": [
        "AMPWeb"
      ],
      "consumerNs": "TV"
    },
    "clickstream": {
      "enabled": true,
      "autoTrackClicks": true,
      "topic": [
        "xp_amp_tv_main",
        "xp_amp_tv_unidentified"
      ],
      "funnel": {
        "enabled": true,
        "topic": "xp_amp_tv_unidentified",
        "constraintProfiles": [
          "AMPFunnel"
        ]
      },
      "impressions": {
        "enabled": true
      }
    },
    "impressions": {
      "viewableThreshold": 1000,
      "viewablePercentage": 0.5
    },
    "performance": {
      "topic": "xp_amp_tv_perf",
      "enabled": true
    },
    "variant": "web"
  },
  "MediaKit": {
    "name": "web-tv-player",
    "version": "1.0"
  },
  "LocaleSwitcher": {
    "locKeys": {
      "ModalTitleText": "WTA.CountrySelector.Title",
      "AfricaMiddleEastIndia": "WTA.CountrySelector.Region.AfricaMiddleEastIndia",
      "AsiaPacific": "WTA.CountrySelector.Region.AsiaPacific",
      "Europe": "WTA.CountrySelector.Region.Europe",
      "LatinAmericaCaribbean": "WTA.CountrySelector.Region.LatinAmericaCaribbean",
      "USCanadaPuertoRico": "WTA.CountrySelector.Region.USCanadaPuertoRico",
      "HeaderPrompt": "WTA.CountrySelector.Header.Prompt",
      "HeaderDoneButton": "WTA.CountrySelector.Done",
      "HeaderDropdownPrompt": "WTA.CountrySelector.ChooseOption"
    }
  },
  "EmberENV": {
    "FEATURES": {},
    "EXTEND_PROTOTYPES": {
      "Date": false
    },
    "_APPLICATION_TEMPLATE_WRAPPER": false,
    "_DEFAULT_ASYNC_OBSERVERS": true,
    "_JQUERY_INTEGRATION": false,
    "_TEMPLATE_ONLY_GLIMMER_COMPONENTS": true
  },
  "APP": {
    "BREAKPOINTS": {
      "xsmall": {
        "min": 300,
        "max": 739
      },
      "small": {
        "min": 740,
        "max": 999
      },
      "medium": {
        "min": 1000,
        "max": 1319
      },
      "large": {
        "min": 1320,
        "max": 1679
      },
      "xlarge": {
        "min": 1680,
        "content": 1680
      }
    },
    "SHARING_TIMER": 1200,
    "SPINNER_DELAY": 1500,
    "FAIL_SPINNER_DELAY": 5000,
    "name": "web-tv-app",
    "version": "2222.6.0+3fd275f6"
  },
  "MEDIA_ARTWORK": {
    "BREAKPOINTS": {
      "xsmall": {
        "min": 300,
        "max": 739
      },
      "small": {
        "min": 740,
        "max": 999
      },
      "medium": {
        "min": 1000,
        "max": 1319
      },
      "large": {
        "min": 1320,
        "max": 1679
      },
      "xlarge": {
        "min": 1680,
        "content": 1680
      }
    },
    "enableWebp": true
  },
  "MEDIA_SHELF": {
    "GRID_CONFIG": {
      "EpicInline": {
        "xsmall": 2.2,
        "small": 4,
        "medium": 5,
        "large": 6,
        "xlarge": 6
      },
      "FullWidth": {
        "xsmall": 1,
        "small": 1,
        "medium": 1,
        "large": 1,
        "xlarge": 1
      },
      "Notes": {
        "xsmall": 1,
        "small": 3,
        "medium": 4,
        "large": 5,
        "xlarge": 5
      },
      "SearchCards": {
        "xsmall": 3,
        "small": 3,
        "medium": 3,
        "large": 3,
        "xlarge": 3
      },
      "UpNext": {
        "xsmall": 1,
        "small": 4,
        "medium": 5,
        "large": 6,
        "xlarge": 6
      },
      "UpNextLockup": {
        "xsmall": 1,
        "small": 3,
        "medium": 4,
        "large": 5,
        "xlarge": 5
      }
    },
    "BREAKPOINTS": {
      "xsmall": {
        "min": 300,
        "max": 739
      },
      "small": {
        "min": 740,
        "max": 999
      },
      "medium": {
        "min": 1000,
        "max": 1319
      },
      "large": {
        "min": 1320,
        "max": 1679
      },
      "xlarge": {
        "min": 1680,
        "content": 1680
      }
    }
  },
  "routerScroll": {
    "scrollWhenIdle": true
  },
  "fastboot": {
    "hostWhitelist": [
      {}
    ]
  },
  "UTS": {
    "webBaseUrl": "https://tv.apple.com/api/uts/"
  },
  "MEDIA_API": {
    "token": "eyJhbGciOiJFUzI1NiIsInR5cCI6IkpXVCIsImtpZCI6IldlYlBsYXlLaWQifQ.eyJpc3MiOiJBTVBXZWJQbGF5IiwiaWF0IjoxNjUzMzI4NTUwLCJleHAiOjE2Njg4ODA1NTAsInJvb3RfaHR0cHNfb3JpZ2luIjpbImFwcGxlLmNvbSJdfQ.g0i-Loh2MNf0KQGMNjupeXFdvafnPyiAmhrUUxFGHGXspqxgmT7vH3LqFxLJ21MXtbeUo_HTqV3sXXaj2mxx_g"
  },
  "RTC": {
    "enabled": true,
    "clientName": "ATVW",
    "applicationName": "AppleTVWeb",
    "serviceName": "com.apple.tv.external",
    "storeBagURL": "https://mediaservices.cdn-apple.com/store_bags/hlsjs/atvw/v1/rtc_storebag.json"
  },
  "features": {
    "TVWEB": true,
    "TV_ON_WEB": false
  },
  "ember-cli-content-security-policy": {
    "policy": "default-src 'self' https://*.apple.com; img-src 'self' https://*.apple.com https://*.mzstatic.com data:; style-src 'self' https://*.apple.com 'unsafe-inline'; script-src 'self' https://*.apple.com blob: 'sha256-4ywTGAe4rEpoHt8XkjbkdOWklMJ/1Py/x6b3/aGbtSQ=' 'unsafe-eval'; connect-src 'self' https://*.apple.com https://*.applemusic.com https://*.mzstatic.com https://mediaservices.cdn-apple.com; media-src 'self' https://*.apple.com https://*.applemusic.com https://*.mzstatic.com blob:; child-src 'self' https://*.apple.com videos: com.apple.tv: blob:; frame-ancestors 'none';",
    "reportOnly": false
  },
  "ember-modal-dialog": {}
}
